panclassif/__init__.py
panclassif/binarymerge.py
panclassif/dataProcess.py
panclassif/featSelect.py
panclassif/gseapy.py
panclassif/models.py
panclassif/multimerge.py
panclassif/stepfive.py
panclassif/stepfour.py
panclassif/stepone.py
panclassif/stepthree.py
panclassif/steptwo.py
panclassif/test_train_split.py
panclassif/upsampling_train_data.py
panclassif-2.1.3.dist-info/LICENSE
panclassif-2.1.3.dist-info/METADATA
panclassif-2.1.3.dist-info/WHEEL
panclassif-2.1.3.dist-info/top_level.txt
panclassif-2.1.3.dist-info/RECORD
