Metadata-Version: 2.1
Name: panclassif
Version: 2.1.3
Summary: A method to improve TCGA pancancer classifiers performance
Home-page: https://github.com/Zwei-inc/panclassif
Author: Md. Robiuddin, Kazi Ferdous Mahin
Author-email: mrrobi040@gmail.com
License: UNKNOWN
Project-URL: Bug Tracker, https://github.com/Zwei-inc/panclassif/issues
Platform: UNKNOWN
Classifier: Programming Language :: Python :: 3
Classifier: License :: OSI Approved :: MIT License
Classifier: Operating System :: OS Independent
Requires-Python: >=3.6
License-File: LICENSE
Requires-Dist: seaborn
Requires-Dist: scikit-learn
Requires-Dist: numpy
Requires-Dist: pandas
Requires-Dist: matplotlib
Requires-Dist: imbalanced-learn
Requires-Dist: tensorflow
Requires-Dist: gseapy
